GradientDescent/__init__.py
GradientDescent/gradient_descent.py
GradientDescent-0.0.2.dist-info/LICENSE
GradientDescent-0.0.2.dist-info/METADATA
GradientDescent-0.0.2.dist-info/WHEEL
GradientDescent-0.0.2.dist-info/top_level.txt
GradientDescent-0.0.2.dist-info/RECORD
