Metadata-Version: 2.1
Name: GradientDescent
Version: 0.0.2
Summary: Makes learning gradient descent easy
Home-page: UNKNOWN
Author: Aayushmaan Jain
Author-email: <aayushmaan1306@gmail.com.com>
License: UNKNOWN
Keywords: python,machine,learning,Machine Learning
Platform: UNKNOWN
Classifier: Development Status :: 1 - Planning
Classifier: Intended Audience :: Developers
Classifier: Programming Language :: Python :: 3
Classifier: Operating System :: Unix
Classifier: Operating System :: MacOS :: MacOS X
Classifier: Operating System :: Microsoft :: Windows
Requires-Dist: numpy
Requires-Dist: pandas
Requires-Dist: sklearn
Requires-Dist: scipy
